pygremlinbox_unlicense/__init__.py
pygremlinbox_unlicense-1.4.0.dist-info/licenses/LICENCE
pygremlinbox_unlicense-1.4.0.dist-info/METADATA
pygremlinbox_unlicense-1.4.0.dist-info/WHEEL
pygremlinbox_unlicense-1.4.0.dist-info/top_level.txt
pygremlinbox_unlicense-1.4.0.dist-info/RECORD
